setup.py
scanjobs/__init__.py
scanjobs/amass.py
scanjobs/ipv4_range.py
scanjobs/scanjob_abc.py
scanjobs.egg-info/PKG-INFO
scanjobs.egg-info/SOURCES.txt
scanjobs.egg-info/dependency_links.txt
scanjobs.egg-info/top_level.txt