Metadata-Version: 2.1
Name: scanjobs
Version: 0.1
Summary: Base classes for scan jobs
Home-page: UNKNOWN
License: MIT
Keywords: nmap,scanning
Platform: UNKNOWN
Classifier: Development Status :: 3 - Alpha
Classifier: Intended Audience :: Developers
Classifier: Topic :: Software Development :: Build Tools
Classifier: License :: OSI Approved :: MIT License
Classifier: Programming Language :: Python :: 3
Classifier: Programming Language :: Python :: 3.4
Classifier: Programming Language :: Python :: 3.5
Classifier: Programming Language :: Python :: 3.6
